pydantic_settings_toml/__init__.py
pydantic_settings_toml/exceptions.py
pydantic_settings_toml/main.py
pydantic_settings_toml/sources.py
pydantic_settings_toml/version.py
pydantic_settings_toml-0.2.0.dist-info/LICENSE
pydantic_settings_toml-0.2.0.dist-info/WHEEL
pydantic_settings_toml-0.2.0.dist-info/METADATA
pydantic_settings_toml-0.2.0.dist-info/RECORD
